jooze-0.1.0.dist-info/METADATA
jooze-0.1.0.dist-info/WHEEL
jooze-0.1.0.dist-info/entry_points.txt
jooze/__init__.py
jooze/__main__.py
jooze/api.py
jooze/app.py
jooze/cli/api.py
jooze/cli/createapp.py
jooze/cli/dev.py
jooze/cli/node.py
jooze/cli/package.py
jooze/codegen.py
jooze/exceptions.py
jooze/lifespan.py
jooze/requirements.txt
jooze/static.py
jooze/templates/docker/.dockerignore-tpl
jooze/templates/docker/Dockerfile-tpl
jooze/templates/docker/docker-compose.yml-tpl
jooze/templates/standard/+app/404.svelte-tpl
jooze/templates/standard/+app/app.css-tpl
jooze/templates/standard/+app/app.svelte-tpl
jooze/templates/standard/+app/index.html-tpl
jooze/templates/standard/+app/index.svelte-tpl
jooze/templates/standard/+app/main.ts
jooze/templates/standard/+node/openapi-ts.config.ts-tpl
jooze/templates/standard/+node/package.json-tpl
jooze/templates/standard/+node/svelte.config.js-tpl
jooze/templates/standard/+node/tsconfig.json-tpl
jooze/templates/standard/+node/vite-env.d.ts-tpl
jooze/templates/standard/+node/vite.config.ts-tpl
jooze/templates/standard/.gitignore-tpl
jooze/templates/standard/README.md-tpl
jooze/templates/standard/example/api.py-tpl
jooze/templates/standard/example/index.svelte-tpl
jooze/templates/standard/main.py-tpl
jooze/templates/standard/requirements.txt-tpl
jooze/templates/standard/tsconfig.json-tpl
jooze-0.1.0.dist-info/RECORD
