Metadata-Version: 2.1
Name: jooze
Version: 0.1.0
Summary: A kit for creating FastAPI + Svelte applications
Author-Email: Channel Cat <channelcat@gmail.com>
License: MIT
Requires-Python: >=3.11
Requires-Dist: aerich[toml]==0.8.1
Requires-Dist: fastapi==0.115.0
Requires-Dist: PyJWT==2.10.1
Requires-Dist: tortoise-orm[asyncpg]==0.24.0
Requires-Dist: typer==0.15.2
Requires-Dist: uvicorn==0.31.0
